__init__.py
__version__.py
constants.py
main.py
models.py
utils.py
validation.py
pdf2joplin-1.0.1.dist-info/licenses/LICENSE
pdf2joplin-1.0.1.dist-info/METADATA
pdf2joplin-1.0.1.dist-info/WHEEL
pdf2joplin-1.0.1.dist-info/entry_points.txt
pdf2joplin-1.0.1.dist-info/top_level.txt
pdf2joplin-1.0.1.dist-info/RECORD
