Metadata-Version: 2.4
Name: pdf2joplin
Version: 1.0.1
Summary: Convert your PDF documents to Markdown notes with KaTeX support with the help of OpenAI.
Author-email: Christos Kaltsas <christos@xcalts.co>
Maintainer-email: Christos Kaltsas <christos@xcalts.co>
License:                     GNU GENERAL PUBLIC LICENSE
Project-URL: Homepage, https://github.com/xcalts/pdf2joplin
Project-URL: Source, https://github.com/xcalts/pdf2joplin
Project-URL: Documentation, https://github.com/xcalts/pdf2joplin
Project-URL: Bug Reports, https://github.com/xcalts/pdf2joplin/issues
Project-URL: Changelog, https://github.com/xcalts/pdf2joplin/releases
Requires-Python: >3.10
License-File: LICENSE
Requires-Dist: Click
Requires-Dist: pdf2image
Requires-Dist: openai
Requires-Dist: pydantic
Dynamic: license-file
